iragent/__init__.py
iragent/agent.py
iragent/memory.py
iragent/message.py
iragent/models.py
iragent/prompts.py
iragent/tools.py
iragent/utility.py
iragent-0.1.9.dist-info/licenses/LICENSE
iragent-0.1.9.dist-info/METADATA
iragent-0.1.9.dist-info/WHEEL
iragent-0.1.9.dist-info/top_level.txt
iragent-0.1.9.dist-info/RECORD
