Metadata-Version: 2.4
Name: iragent
Version: 0.1.9
Summary: A simple multi-agent framework
Author-email: Parsa Bakhtiari <spacenavard1@gmail.com>
License: MIT
Requires-Python: >=3.10
License-File: LICENSE
Requires-Dist: openai
Requires-Dist: requests
Requires-Dist: googlesearch-python
Requires-Dist: beautifulsoup4
Requires-Dist: lxml
Requires-Dist: nltk
Requires-Dist: pytest
Requires-Dist: tiktoken
Requires-Dist: numpy
Provides-Extra: rag
Requires-Dist: faiss-cpu; extra == "rag"
Requires-Dist: sentence-transformers; extra == "rag"
Provides-Extra: rag-gpu
Requires-Dist: faiss-gpu; extra == "rag-gpu"
Requires-Dist: sentence-transformers; extra == "rag-gpu"
Dynamic: license-file
